topsis_sanchit/topsis.py
Topsis_Sanchit_101917123-0.0.2.dist-info/LICENSE
Topsis_Sanchit_101917123-0.0.2.dist-info/METADATA
Topsis_Sanchit_101917123-0.0.2.dist-info/WHEEL
Topsis_Sanchit_101917123-0.0.2.dist-info/entry_points.txt
Topsis_Sanchit_101917123-0.0.2.dist-info/top_level.txt
Topsis_Sanchit_101917123-0.0.2.dist-info/RECORD
