Metadata-Version: 2.1
Name: Topsis-Sanchit-101917123
Version: 0.0.2
Summary: A package -> Calculates Topsis Score and Rank them accordingly
Home-page: https://github.com/sanchit36/topsis_sanchit
Author: Sanchit Bhadgal
Author-email: sanchitbhadgal36@gmail.com
License: MIT
Platform: UNKNOWN
Classifier: Programming Language :: Python :: 3
Classifier: License :: OSI Approved :: MIT License
Classifier: Operating System :: OS Independent
License-File: LICENSE
Requires-Dist: pandas
